{"name": "Sircilla", "lsg_code": "251654", "district": "Rajanna Sircilla", "state": "Telangana", "no_of_wards": 39, "wards": [{"ward_no": "28", "ward_name": "Sircilla (M) - Ward No.28", "ward_id": "2429"}, {"ward_no": "11", "ward_name": "Sircilla (M) - Ward No.11", "ward_id": "51007"}, {"ward_no": "21", "ward_name": "Sircilla (M) - Ward No.21", "ward_id": "2422"}, {"ward_no": "32", "ward_name": "Sircilla Ward No 32", "ward_id": "126647"}, {"ward_no": "7", "ward_name": "Sircilla (M) - Ward No.7", "ward_id": "51003"}, {"ward_no": "12", "ward_name": "Sircilla (M) - Ward No.12", "ward_id": "51008"}, {"ward_no": "5", "ward_name": "Sircilla (M) - Ward No.5", "ward_id": "51001"}, {"ward_no": "33", "ward_name": "Sircilla Ward No 33", "ward_id": "126648"}, {"ward_no": "39", "ward_name": "Sircilla Ward No39", "ward_id": "2519762"}, {"ward_no": "37", "ward_name": "Sircilla Ward No37", "ward_id": "2519760"}, {"ward_no": "25", "ward_name": "Sircilla (M) - Ward No.25", "ward_id": "2426"}, {"ward_no": "8", "ward_name": "Sircilla (M) - Ward No.8", "ward_id": "51004"}, {"ward_no": "20", "ward_name": "Sircilla (M) - Ward No.20", "ward_id": "2421"}, {"ward_no": "36", "ward_name": "Sircilla Ward No36", "ward_id": "2519759"}, {"ward_no": "15", "ward_name": "Sircilla (M) - Ward No.15", "ward_id": "2415"}, {"ward_no": "31", "ward_name": "Sircilla Ward No 31", "ward_id": "126646"}, {"ward_no": "27", "ward_name": "Sircilla (M) - Ward No.27", "ward_id": "2428"}, {"ward_no": "10", "ward_name": "Sircilla (M) - Ward No.10", "ward_id": "51006"}, {"ward_no": "22", "ward_name": "Sircilla (M) - Ward No.22", "ward_id": "2423"}, {"ward_no": "18", "ward_name": "Sircilla (M) - Ward No.18", "ward_id": "2419"}, {"ward_no": "38", "ward_name": "Sircilla Ward No38", "ward_id": "2519761"}, {"ward_no": "6", "ward_name": "Sircilla (M) - Ward No.6", "ward_id": "51002"}, {"ward_no": "34", "ward_name": "Sircilla Ward No34", "ward_id": "2519757"}, {"ward_no": "16", "ward_name": "Sircilla (M) - Ward No.16", "ward_id": "2417"}, {"ward_no": "14", "ward_name": "Sircilla (M) - Ward No.14", "ward_id": "2414"}, {"ward_no": "35", "ward_name": "Sircilla Ward No35", "ward_id": "2519758"}, {"ward_no": "9", "ward_name": "Sircilla (M) - Ward No.9", "ward_id": "51005"}, {"ward_no": "19", "ward_name": "Sircilla (M) - Ward No.19", "ward_id": "2420"}, {"ward_no": "2", "ward_name": "Sircilla (M) - Ward No.2", "ward_id": "50998"}, {"ward_no": "4", "ward_name": "Sircilla (M) - Ward No.4", "ward_id": "51000"}, {"ward_no": "17", "ward_name": "Sircilla (M) - Ward No.17", "ward_id": "2418"}, {"ward_no": "23", "ward_name": "Sircilla (M) - Ward No.23", "ward_id": "2424"}, {"ward_no": "26", "ward_name": "Sircilla (M) - Ward No.26", "ward_id": "2427"}, {"ward_no": "13", "ward_name": "Sircilla (M) - Ward No.13", "ward_id": "2413"}, {"ward_no": "30", "ward_name": "Sircilla Ward No 30", "ward_id": "126645"}, {"ward_no": "24", "ward_name": "Sircilla (M) - Ward No.24", "ward_id": "2425"}, {"ward_no": "3", "ward_name": "Sircilla (M) - Ward No.3", "ward_id": "50999"}, {"ward_no": "29", "ward_name": "Sircilla (M) - Ward No.29", "ward_id": "2430"}, {"ward_no": "1", "ward_name": "Sircilla (M) - Ward No.1", "ward_id": "50997"}]}
