{"name": "Vyara", "lsg_code": "251244", "district": "Tapi", "state": "Gujarat", "no_of_wards": 7, "wards": [{"ward_no": "5", "ward_name": "Vyara (M) - Ward No.5", "ward_id": "67736"}, {"ward_no": "3", "ward_name": "Vyara (M) - Ward No.3", "ward_id": "67734"}, {"ward_no": "6", "ward_name": "Vyara (M) - Ward No.6", "ward_id": "67737"}, {"ward_no": "2", "ward_name": "Vyara (M) - Ward No.2", "ward_id": "67733"}, {"ward_no": "4", "ward_name": "Vyara (M) - Ward No.4", "ward_id": "67735"}, {"ward_no": "1", "ward_name": "Vyara (M) - Ward No.1", "ward_id": "67732"}, {"ward_no": "7", "ward_name": "Vyara (M) - Ward No.7", "ward_id": "67738"}]}
