{"name": "Badawada", "lsg_code": "250838", "district": "Ratlam", "state": "Madhya Pradesh", "no_of_wards": 15, "wards": [{"ward_no": "2", "ward_name": "Ambedkar Ward", "ward_id": "5252"}, {"ward_no": "3", "ward_name": "Shivaji Ward", "ward_id": "5253"}, {"ward_no": "8", "ward_name": "Shastri Ward", "ward_id": "5258"}, {"ward_no": "6", "ward_name": "Bhagat Singh Ward", "ward_id": "5256"}, {"ward_no": "14", "ward_name": "Rajendra Prasad Ward", "ward_id": "5264"}, {"ward_no": "9", "ward_name": "Laxmibai Ward", "ward_id": "5259"}, {"ward_no": "12", "ward_name": "Indira Gandhi Ward", "ward_id": "5262"}, {"ward_no": "15", "ward_name": "Chandrashekhar Ward", "ward_id": "5265"}, {"ward_no": "10", "ward_name": "Subhash Ward", "ward_id": "5260"}, {"ward_no": "4", "ward_name": "Jawahar ward", "ward_id": "5254"}, {"ward_no": "1", "ward_name": "Mahatma Gandhi Ward", "ward_id": "5251"}, {"ward_no": "13", "ward_name": "Rana Pratap Ward", "ward_id": "5263"}, {"ward_no": "5", "ward_name": "Maulana Azad Ward", "ward_id": "5255"}, {"ward_no": "7", "ward_name": "Patel Ward", "ward_id": "5257"}, {"ward_no": "11", "ward_name": "Mukherjee Ward", "ward_id": "5261"}]}
