{"name": "Jaspur", "lsg_code": "248462", "district": "Udam Singh Nagar", "state": "Uttarakhand", "no_of_wards": 20, "wards": [{"ward_no": "7", "ward_name": "Jaspur (MB) - Julahaan Dakshini Ward No.7", "ward_id": "18491"}, {"ward_no": "8", "ward_name": "Jaspur (MB) - Patti Chauhan Purvi Ward No.8", "ward_id": "18492"}, {"ward_no": "10", "ward_name": "Jaspur (MB) - Bhoop Singh Dakshini Ward No.10", "ward_id": "18494"}, {"ward_no": "4", "ward_name": "Jaspur (MB) - Gujratiyan Uttari Ward No.4", "ward_id": "18488"}, {"ward_no": "15", "ward_name": "Jaspur (MB) - Nayi Bashti Purvi Gaanguwala Ward No.15", "ward_id": "1296513"}, {"ward_no": "18", "ward_name": "Jaspur (MB) - Nayi Bashti Uttari Paschami Ward No.18", "ward_id": "1296516"}, {"ward_no": "11", "ward_name": "Jaspur (MB) - Bazaar Bhoop Singh Uttari Ward No.11", "ward_id": "18495"}, {"ward_no": "20", "ward_name": "Jaspur (MB) - Nayi Bashti Paschami Dakshini Ward No.20", "ward_id": "1296518"}, {"ward_no": "3", "ward_name": "Jaspur (MB) - Natha Singh Paschami Ward No.3", "ward_id": "18487"}, {"ward_no": "9", "ward_name": "Jaspur (MB) - Patti Chauhan Paschami Ward No.9", "ward_id": "18493"}, {"ward_no": "12", "ward_name": "Jaspur (MB) - Chipiyan Purvi Ward No.12", "ward_id": "18496"}, {"ward_no": "14", "ward_name": "Jaspur (MB) - Nayi Bashti Purvi Ward No.14", "ward_id": "1296512"}, {"ward_no": "16", "ward_name": "Jaspur (MB) - Nayi Bashti Purvi Ward No.16", "ward_id": "1296514"}, {"ward_no": "1", "ward_name": "Jaspur (MB) - Dilla Singh Ward No.1", "ward_id": "18485"}, {"ward_no": "13", "ward_name": "Jaspur (MB) - Chipiyan Paschami Ward No.13", "ward_id": "18497"}, {"ward_no": "5", "ward_name": "Jaspur (MB) - Gujratiyan Dakshini Ward No.5", "ward_id": "18489"}, {"ward_no": "2", "ward_name": "Jaspur (MB) - Natha Singh Purvi Ward No.2", "ward_id": "18486"}, {"ward_no": "17", "ward_name": "Jaspur (MB) - Nayi Bashti Madhyamik Paschami Ward No.17", "ward_id": "1296515"}, {"ward_no": "19", "ward_name": "Jaspur (MB) - Nayi Bashti Purvi Dakshini Ward No.19", "ward_id": "1296517"}, {"ward_no": "6", "ward_name": "Jaspur (MB) - Julahaan Uttari Ward No.6", "ward_id": "18490"}]}
