{"name": "Lalgudi", "lsg_code": "252747", "district": "Tiruchirappalli", "state": "Tamil Nadu", "no_of_wards": 18, "wards": [{"ward_no": "6", "ward_name": "Lalgudi (TP) - Ward No.6", "ward_id": "39059"}, {"ward_no": "13", "ward_name": "Lalgudi (TP) - Ward No.13", "ward_id": "39066"}, {"ward_no": "8", "ward_name": "Lalgudi (TP) - Ward No.8", "ward_id": "39061"}, {"ward_no": "15", "ward_name": "Lalgudi (TP) - Ward No.15", "ward_id": "39068"}, {"ward_no": "17", "ward_name": "Lalgudi (TP) - Ward No.17", "ward_id": "39070"}, {"ward_no": "18", "ward_name": "Lalgudi (TP) - Ward No.18", "ward_id": "39071"}, {"ward_no": "14", "ward_name": "Lalgudi (TP) - Ward No.14", "ward_id": "39067"}, {"ward_no": "9", "ward_name": "Lalgudi (TP) - Ward No.9", "ward_id": "39062"}, {"ward_no": "3", "ward_name": "Lalgudi (TP) - Ward No.3", "ward_id": "39056"}, {"ward_no": "10", "ward_name": "Lalgudi (TP) - Ward No.10", "ward_id": "39063"}, {"ward_no": "1", "ward_name": "Lalgudi (TP) - Ward No.1", "ward_id": "39054"}, {"ward_no": "7", "ward_name": "Lalgudi (TP) - Ward No.7", "ward_id": "39060"}, {"ward_no": "2", "ward_name": "Lalgudi (TP) - Ward No.2", "ward_id": "39055"}, {"ward_no": "12", "ward_name": "Lalgudi (TP) - Ward No.12", "ward_id": "39065"}, {"ward_no": "4", "ward_name": "Lalgudi (TP) - Ward No.4", "ward_id": "39057"}, {"ward_no": "11", "ward_name": "Lalgudi (TP) - Ward No.11", "ward_id": "39064"}, {"ward_no": "16", "ward_name": "Lalgudi (TP) - Ward No.16", "ward_id": "39069"}, {"ward_no": "5", "ward_name": "Lalgudi (TP) - Ward No.5", "ward_id": "39058"}]}
