{"name": "Khaniyadhana", "lsg_code": "250711", "district": "Shivpuri", "state": "Madhya Pradesh", "no_of_wards": 15, "wards": [{"ward_no": "12", "ward_name": "MAHARANI LAXMI BAI WARD", "ward_id": "7528"}, {"ward_no": "14", "ward_name": "Shastri Ward", "ward_id": "7530"}, {"ward_no": "1", "ward_name": "Tilak Ward", "ward_id": "7517"}, {"ward_no": "3", "ward_name": "Nehru ward", "ward_id": "7519"}, {"ward_no": "4", "ward_name": "Subhash Ward", "ward_id": "7520"}, {"ward_no": "15", "ward_name": "Khalakh Singh Ward", "ward_id": "7531"}, {"ward_no": "6", "ward_name": "Chandrashekhar Ward", "ward_id": "7522"}, {"ward_no": "13", "ward_name": "Lohia Ward", "ward_id": "7529"}, {"ward_no": "7", "ward_name": "Bhagat Singh Ward", "ward_id": "7523"}, {"ward_no": "10", "ward_name": "Pratap Ward", "ward_id": "7526"}, {"ward_no": "11", "ward_name": "Shivaji Ward", "ward_id": "7527"}, {"ward_no": "8", "ward_name": "Ambedkar Ward", "ward_id": "7524"}, {"ward_no": "5", "ward_name": "Hrdul Ward", "ward_id": "7521"}, {"ward_no": "9", "ward_name": "Gandhi ward", "ward_id": "7525"}, {"ward_no": "2", "ward_name": "Indira Gandhi ward", "ward_id": "7518"}]}
