{"name": "Dhule", "lsg_code": "251282", "district": "Dhule", "state": "Maharashtra", "no_of_wards": 70, "wards": [{"ward_no": "7", "ward_name": "Dhule (M Cl) - Ward No.7", "ward_id": "55288"}, {"ward_no": "35", "ward_name": "Dhule (M Cl) - Ward No.35", "ward_id": "55316"}, {"ward_no": "22", "ward_name": "Dhule (M Cl) - Ward No.22", "ward_id": "55303"}, {"ward_no": "48", "ward_name": "Dhule (M Cl) - Ward No.48", "ward_id": "55329"}, {"ward_no": "67", "ward_name": "Dhule (M Cl) - Ward No.67", "ward_id": "71891"}, {"ward_no": "9", "ward_name": "Dhule (M Cl) - Ward No.9", "ward_id": "55290"}, {"ward_no": "57", "ward_name": "Dhule (M Cl) - Ward No.57", "ward_id": "55338"}, {"ward_no": "63", "ward_name": "Dhule (M Cl) - Ward No.63", "ward_id": "71887"}, {"ward_no": "66", "ward_name": "Dhule (M Cl) - Ward No.66", "ward_id": "71890"}, {"ward_no": "6", "ward_name": "Dhule (M Cl) - Ward No.6", "ward_id": "55287"}, {"ward_no": "24", "ward_name": "Dhule (M Cl) - Ward No.24", "ward_id": "55305"}, {"ward_no": "64", "ward_name": "Dhule (M Cl) - Ward No.64", "ward_id": "71888"}, {"ward_no": "20", "ward_name": "Dhule (M Cl) - Ward No.20", "ward_id": "55301"}, {"ward_no": "34", "ward_name": "Dhule (M Cl) - Ward No.34", "ward_id": "55315"}, {"ward_no": "38", "ward_name": "Dhule (M Cl) - Ward No.38", "ward_id": "55319"}, {"ward_no": "5", "ward_name": "Dhule (M Cl) - Ward No.5", "ward_id": "55286"}, {"ward_no": "25", "ward_name": "Dhule (M Cl) - Ward No.25", "ward_id": "55306"}, {"ward_no": "30", "ward_name": "Dhule (M Cl) - Ward No.30", "ward_id": "55311"}, {"ward_no": "70", "ward_name": "Dhule (M Cl) - Ward No.70", "ward_id": "889608"}, {"ward_no": "10", "ward_name": "Dhule (M Cl) - Ward No.10", "ward_id": "55291"}, {"ward_no": "53", "ward_name": "Dhule (M Cl) - Ward No.53", "ward_id": "55334"}, {"ward_no": "11", "ward_name": "Dhule (M Cl) - Ward No.11", "ward_id": "55292"}, {"ward_no": "32", "ward_name": "Dhule (M Cl) - Ward No.32", "ward_id": "55313"}, {"ward_no": "27", "ward_name": "Dhule (M Cl) - Ward No.27", "ward_id": "55308"}, {"ward_no": "17", "ward_name": "Dhule (M Cl) - Ward No.17", "ward_id": "55298"}, {"ward_no": "33", "ward_name": "Dhule (M Cl) - Ward No.33", "ward_id": "55314"}, {"ward_no": "31", "ward_name": "Dhule (M Cl) - Ward No.31", "ward_id": "55312"}, {"ward_no": "45", "ward_name": "Dhule (M Cl) - Ward No.45", "ward_id": "55326"}, {"ward_no": "44", "ward_name": "Dhule (M Cl) - Ward No.44", "ward_id": "55325"}, {"ward_no": "19", "ward_name": "Dhule (M Cl) - Ward No.19", "ward_id": "55300"}, {"ward_no": "68", "ward_name": "Dhule (M Cl) - Ward No.68", "ward_id": "889605"}, {"ward_no": "2", "ward_name": "Dhule (M Cl) - Ward No.2", "ward_id": "55283"}, {"ward_no": "54", "ward_name": "Dhule (M Cl) - Ward No.54", "ward_id": "55335"}, {"ward_no": "26", "ward_name": "Dhule (M Cl) - Ward No.26", "ward_id": "55307"}, {"ward_no": "65", "ward_name": "Dhule (M Cl) - Ward No.65", "ward_id": "71889"}, {"ward_no": "61", "ward_name": "Dhule (M Cl) - Ward No.61", "ward_id": "71885"}, {"ward_no": "49", "ward_name": "Dhule (M Cl) - Ward No.49", "ward_id": "55330"}, {"ward_no": "50", "ward_name": "Dhule (M Cl) - Ward No.50", "ward_id": "55331"}, {"ward_no": "15", "ward_name": "Dhule (M Cl) - Ward No.15", "ward_id": "55296"}, {"ward_no": "18", "ward_name": "Dhule (M Cl) - Ward No.18", "ward_id": "55299"}, {"ward_no": "12", "ward_name": "Dhule (M Cl) - Ward No.12", "ward_id": "55293"}, {"ward_no": "60", "ward_name": "Dhule (M Cl) - Ward No.60", "ward_id": "55341"}, {"ward_no": "59", "ward_name": "Dhule (M Cl) - Ward No.59", "ward_id": "55340"}, {"ward_no": "37", "ward_name": "Dhule (M Cl) - Ward No.37", "ward_id": "55318"}, {"ward_no": "8", "ward_name": "Dhule (M Cl) - Ward No.8", "ward_id": "55289"}, {"ward_no": "4", "ward_name": "Dhule (M Cl) - Ward No.4", "ward_id": "55285"}, {"ward_no": "55", "ward_name": "Dhule (M Cl) - Ward No.55", "ward_id": "55336"}, {"ward_no": "46", "ward_name": "Dhule (M Cl) - Ward No.46", "ward_id": "55327"}, {"ward_no": "40", "ward_name": "Dhule (M Cl) - Ward No.40", "ward_id": "55321"}, {"ward_no": "28", "ward_name": "Dhule (M Cl) - Ward No.28", "ward_id": "55309"}, {"ward_no": "58", "ward_name": "Dhule (M Cl) - Ward No.58", "ward_id": "55339"}, {"ward_no": "42", "ward_name": "Dhule (M Cl) - Ward No.42", "ward_id": "55323"}, {"ward_no": "52", "ward_name": "Dhule (M Cl) - Ward No.52", "ward_id": "55333"}, {"ward_no": "21", "ward_name": "Dhule (M Cl) - Ward No.21", "ward_id": "55302"}, {"ward_no": "3", "ward_name": "Dhule (M Cl) - Ward No.3", "ward_id": "55284"}, {"ward_no": "14", "ward_name": "Dhule (M Cl) - Ward No.14", "ward_id": "55295"}, {"ward_no": "43", "ward_name": "Dhule (M Cl) - Ward No.43", "ward_id": "55324"}, {"ward_no": "36", "ward_name": "Dhule (M Cl) - Ward No.36", "ward_id": "55317"}, {"ward_no": "13", "ward_name": "Dhule (M Cl) - Ward No.13", "ward_id": "55294"}, {"ward_no": "23", "ward_name": "Dhule (M Cl) - Ward No.23", "ward_id": "55304"}, {"ward_no": "47", "ward_name": "Dhule (M Cl) - Ward No.47", "ward_id": "55328"}, {"ward_no": "39", "ward_name": "Dhule (M Cl) - Ward No.39", "ward_id": "55320"}, {"ward_no": "62", "ward_name": "Dhule (M Cl) - Ward No.62", "ward_id": "71886"}, {"ward_no": "41", "ward_name": "Dhule (M Cl) - Ward No.41", "ward_id": "55322"}, {"ward_no": "16", "ward_name": "Dhule (M Cl) - Ward No.16", "ward_id": "55297"}, {"ward_no": "29", "ward_name": "Dhule (M Cl) - Ward No.29", "ward_id": "55310"}, {"ward_no": "69", "ward_name": "Dhule (M Cl) - Ward No.69", "ward_id": "889607"}, {"ward_no": "51", "ward_name": "Dhule (M Cl) - Ward No.51", "ward_id": "55332"}, {"ward_no": "1", "ward_name": "Dhule (M Cl) - Ward No.1", "ward_id": "55282"}, {"ward_no": "56", "ward_name": "Dhule (M Cl) - Ward No.56", "ward_id": "55337"}]}
