{"name": "Teonthar", "lsg_code": "250789", "district": "Rewa", "state": "Madhya Pradesh", "no_of_wards": 15, "wards": [{"ward_no": "4", "ward_name": "Lal Bahadur Shastri Ward", "ward_id": "12146"}, {"ward_no": "15", "ward_name": "Bal Ganga Dhar Tilak ward", "ward_id": "12157"}, {"ward_no": "6", "ward_name": "Dr Bhim Rao Ambedkar Ward", "ward_id": "12148"}, {"ward_no": "2", "ward_name": "Pt. Jawaharlal Nehru ward", "ward_id": "12144"}, {"ward_no": "12", "ward_name": "Mahatma Ghandhi Ward", "ward_id": "12154"}, {"ward_no": "11", "ward_name": "Maharana Pratap Singh Ward", "ward_id": "12153"}, {"ward_no": "10", "ward_name": "Netaji Subhash Chandra Bose Ward", "ward_id": "12152"}, {"ward_no": "8", "ward_name": "Pt Dindayal ward", "ward_id": "12150"}, {"ward_no": "9", "ward_name": "Dr Ram manohar lohiya", "ward_id": "12151"}, {"ward_no": "3", "ward_name": "Shaheed Padamdheer singh ward", "ward_id": "12145"}, {"ward_no": "5", "ward_name": "SARDAR VALLABH BHAI PATEL WARD", "ward_id": "12147"}, {"ward_no": "7", "ward_name": "Ravindra nath tagore", "ward_id": "12149"}, {"ward_no": "14", "ward_name": "Prithvi Raj Singh Chauhan ward", "ward_id": "12156"}, {"ward_no": "13", "ward_name": "SANJAY GANDHI WARD", "ward_id": "12155"}, {"ward_no": "1", "ward_name": "Shaheed Bhagat Singh ward", "ward_id": "12143"}]}
