{"name": "Shivrinarayan", "lsg_code": "250604", "district": "Janjgir-Champa", "state": "Chhattisgarh", "no_of_wards": 15, "wards": [{"ward_no": "6", "ward_name": "Mahatma Gandhi Ward", "ward_id": "32742"}, {"ward_no": "12", "ward_name": "Bhagat Siongh Ward", "ward_id": "32748"}, {"ward_no": "4", "ward_name": "Math Ward", "ward_id": "32740"}, {"ward_no": "15", "ward_name": "Sethinagar Ward", "ward_id": "32751"}, {"ward_no": "1", "ward_name": "JanakPur Ward", "ward_id": "32737"}, {"ward_no": "7", "ward_name": "Azad Chandra Shekhar Ward", "ward_id": "32743"}, {"ward_no": "3", "ward_name": "Nishad Ward", "ward_id": "32739"}, {"ward_no": "9", "ward_name": "Subhash Chandra Bose Ward", "ward_id": "32745"}, {"ward_no": "5", "ward_name": "Bhagwan Shivrinarayan Ward", "ward_id": "32741"}, {"ward_no": "8", "ward_name": "Pt. Nehru Ward", "ward_id": "32744"}, {"ward_no": "11", "ward_name": "Vidya Nagar Ward", "ward_id": "32747"}, {"ward_no": "2", "ward_name": "Agrasen Ward", "ward_id": "32738"}, {"ward_no": "10", "ward_name": "Ambedkar Ward", "ward_id": "32746"}, {"ward_no": "14", "ward_name": "Nath Baba Ward", "ward_id": "32750"}, {"ward_no": "13", "ward_name": "Thakur Dev Ward", "ward_id": "32749"}]}
