{"name": "Mailani", "lsg_code": "249178", "district": "Kheri", "state": "Uttar Pradesh", "no_of_wards": 11, "wards": [{"ward_no": "3", "ward_name": "Mailani (NP) - Ward No.3", "ward_id": "31491"}, {"ward_no": "11", "ward_name": "Mailani (NP) - Ward No.11", "ward_id": "31499"}, {"ward_no": "4", "ward_name": "Mailani (NP) - Ward No.4", "ward_id": "31492"}, {"ward_no": "8", "ward_name": "Mailani (NP) - Ward No.8", "ward_id": "31496"}, {"ward_no": "1", "ward_name": "Mailani (NP) - Ward No.1", "ward_id": "31489"}, {"ward_no": "10", "ward_name": "Mailani (NP) - Ward No.10", "ward_id": "31498"}, {"ward_no": "7", "ward_name": "Mailani (NP) - Ward No.7", "ward_id": "31495"}, {"ward_no": "2", "ward_name": "Mailani (NP) - Ward No.2", "ward_id": "31490"}, {"ward_no": "9", "ward_name": "Mailani (NP) - Ward No.9", "ward_id": "31497"}, {"ward_no": "5", "ward_name": "Mailani (NP) - Ward No.5", "ward_id": "31493"}, {"ward_no": "6", "ward_name": "Mailani (NP) - Ward No.6", "ward_id": "31494"}]}
