{"name": "Amila", "lsg_code": "249484", "district": "Mau", "state": "Uttar Pradesh", "no_of_wards": 10, "wards": [{"ward_no": "1", "ward_name": "Amila (NP) - Ward No.1", "ward_id": "6406"}, {"ward_no": "3", "ward_name": "Amila (NP) - Ward No.3", "ward_id": "6408"}, {"ward_no": "4", "ward_name": "Amila (NP) - Ward No.4", "ward_id": "6409"}, {"ward_no": "8", "ward_name": "Amila (NP) - Ward No.8", "ward_id": "6413"}, {"ward_no": "5", "ward_name": "Amila (NP) - Ward No.5", "ward_id": "6410"}, {"ward_no": "2", "ward_name": "Amila (NP) - Ward No.2", "ward_id": "6407"}, {"ward_no": "9", "ward_name": "Amila (NP) - Ward No.9", "ward_id": "6414"}, {"ward_no": "6", "ward_name": "Amila (NP) - Ward No.6", "ward_id": "6411"}, {"ward_no": "10", "ward_name": "Amila (NP) - Ward No.10", "ward_id": "6415"}, {"ward_no": "7", "ward_name": "Amila (NP) - Ward No.7", "ward_id": "6412"}]}
