{"name": "Pattinam", "lsg_code": "252511", "district": "Namakkal", "state": "Tamil Nadu", "no_of_wards": 15, "wards": [{"ward_no": "15", "ward_name": "Pattinam (TP) - Ward No.15", "ward_id": "41287"}, {"ward_no": "13", "ward_name": "Pattinam (TP) - Ward No.13", "ward_id": "41285"}, {"ward_no": "1", "ward_name": "Pattinam (TP) - Ward No.1", "ward_id": "40800"}, {"ward_no": "3", "ward_name": "Pattinam (TP) - Ward No.3", "ward_id": "40802"}, {"ward_no": "11", "ward_name": "Pattinam (TP) - Ward No.11", "ward_id": "40810"}, {"ward_no": "8", "ward_name": "Pattinam (TP) - Ward No.8", "ward_id": "40807"}, {"ward_no": "6", "ward_name": "Pattinam (TP) - Ward No.6", "ward_id": "40805"}, {"ward_no": "5", "ward_name": "Pattinam (TP) - Ward No.5", "ward_id": "40804"}, {"ward_no": "4", "ward_name": "Pattinam (TP) - Ward No.4", "ward_id": "40803"}, {"ward_no": "2", "ward_name": "Pattinam (TP) - Ward No.2", "ward_id": "40801"}, {"ward_no": "7", "ward_name": "Pattinam (TP) - Ward No.7", "ward_id": "40806"}, {"ward_no": "14", "ward_name": "Pattinam (TP) - Ward No.14", "ward_id": "41286"}, {"ward_no": "12", "ward_name": "Pattinam (TP) - Ward No.12", "ward_id": "41284"}, {"ward_no": "9", "ward_name": "Pattinam (TP) - Ward No.9", "ward_id": "40808"}, {"ward_no": "10", "ward_name": "Pattinam (TP) - Ward No.10", "ward_id": "40809"}]}
