{"name": "SANGAIKOT", "lsg_code": "30", "district": "CHURACHANDPUR", "state": "MANIPUR", "no_of_wards": 103, "wards": [{"ward_no": "0", "ward_name": "B.Kaljang", "ward_id": "0"}, {"ward_no": "0", "ward_name": "B.Pangmual", "ward_id": "0"}, {"ward_no": "0", "ward_name": "B.Salvaphai", "ward_id": "0"}, {"ward_no": "0", "ward_name": "Chaljang", "ward_id": "0"}, {"ward_no": "0", "ward_name": "Damjol", "ward_id": "0"}, {"ward_no": "0", "ward_name": "D. Jangnom", "ward_id": "0"}, {"ward_no": "0", "ward_name": "D. Khovangchoi", "ward_id": "0"}, {"ward_no": "0", "ward_name": "Dongjang", "ward_id": "0"}, {"ward_no": "0", "ward_name": "Dumlian (Salem)", "ward_id": "0"}, {"ward_no": "0", "ward_name": "Dutezol", "ward_id": "0"}, {"ward_no": "0", "ward_name": "G.Gamphajol", "ward_id": "0"}, {"ward_no": "0", "ward_name": "G.Khonuam", "ward_id": "0"}, {"ward_no": "0", "ward_name": "G.Molkon", "ward_id": "0"}, {"ward_no": "0", "ward_name": "G. Monglian", "ward_id": "0"}, {"ward_no": "0", "ward_name": "Goupibung", "ward_id": "0"}, {"ward_no": "0", "ward_name": "Govajang", "ward_id": "0"}, {"ward_no": "0", "ward_name": "Gunphai", "ward_id": "0"}, {"ward_no": "0", "ward_name": "Haopi", "ward_id": "0"}, {"ward_no": "0", "ward_name": "Haopijang", "ward_id": "0"}, {"ward_no": "0", "ward_name": "Haopi Vangmun", "ward_id": "0"}, {"ward_no": "0", "ward_name": "H. Bollen", "ward_id": "0"}, {"ward_no": "0", "ward_name": "Hengken", "ward_id": "0"}, {"ward_no": "0", "ward_name": "Hita Khunou", "ward_id": "0"}, {"ward_no": "0", "ward_name": "Jangmun", "ward_id": "0"}, {"ward_no": "0", "ward_name": "Kangleiphai", "ward_id": "0"}, {"ward_no": "0", "ward_name": "Khuangkhaijang", "ward_id": "0"}, {"ward_no": "0", "ward_name": "K. Janglenphai", "ward_id": "0"}, {"ward_no": "0", "ward_name": "K.Jangnomphai", "ward_id": "0"}, {"ward_no": "0", "ward_name": "K.Munhoi", "ward_id": "0"}, {"ward_no": "0", "ward_name": "K.Siroi", "ward_id": "0"}, {"ward_no": "0", "ward_name": "Kuwan", "ward_id": "0"}, {"ward_no": "0", "ward_name": "L.Alpha", "ward_id": "0"}, {"ward_no": "0", "ward_name": "Lamlai", "ward_id": "0"}, {"ward_no": "0", "ward_name": "Langvon", "ward_id": "0"}, {"ward_no": "0", "ward_name": "L.Gangpimual", "ward_id": "0"}, {"ward_no": "0", "ward_name": "Lhangnom", "ward_id": "0"}, {"ward_no": "0", "ward_name": "L. KHAUKUAL", "ward_id": "0"}, {"ward_no": "0", "ward_name": "L. Khonomphai", "ward_id": "0"}, {"ward_no": "0", "ward_name": "L. Molnoi", "ward_id": "0"}, {"ward_no": "0", "ward_name": "L. Muncham", "ward_id": "0"}, {"ward_no": "0", "ward_name": "Loibual", "ward_id": "0"}, {"ward_no": "0", "ward_name": "L.Phainom", "ward_id": "0"}, {"ward_no": "0", "ward_name": "L.Songjangpat", "ward_id": "0"}, {"ward_no": "0", "ward_name": "Luihoihmolcham", "ward_id": "0"}, {"ward_no": "0", "ward_name": "Lunggil", "ward_id": "0"}, {"ward_no": "0", "ward_name": "Makhao Bungmual", "ward_id": "0"}, {"ward_no": "0", "ward_name": "Makhao (H)", "ward_id": "0"}, {"ward_no": "0", "ward_name": "Makhao Mollum", "ward_id": "0"}, {"ward_no": "0", "ward_name": "Makhao Tampak", "ward_id": "0"}, {"ward_no": "0", "ward_name": "Matijang", "ward_id": "0"}, {"ward_no": "0", "ward_name": "M.B.Saichang", "ward_id": "0"}, {"ward_no": "0", "ward_name": "M.Haopi Mollen", "ward_id": "0"}, {"ward_no": "0", "ward_name": "M.kholmual", "ward_id": "0"}, {"ward_no": "0", "ward_name": "MN Tatjang", "ward_id": "0"}, {"ward_no": "0", "ward_name": "Moldenphai", "ward_id": "0"}, {"ward_no": "0", "ward_name": "Molphai", "ward_id": "0"}, {"ward_no": "0", "ward_name": "Molvom (Srs)", "ward_id": "0"}, {"ward_no": "0", "ward_name": "Mongbung", "ward_id": "0"}, {"ward_no": "0", "ward_name": "Mongnelphai", "ward_id": "0"}, {"ward_no": "0", "ward_name": "M.Phaimol", "ward_id": "0"}, {"ward_no": "0", "ward_name": "M.Phainom", "ward_id": "0"}, {"ward_no": "0", "ward_name": "M.Saheiphai", "ward_id": "0"}, {"ward_no": "0", "ward_name": "M.Teijang", "ward_id": "0"}, {"ward_no": "0", "ward_name": "Muizol", "ward_id": "0"}, {"ward_no": "0", "ward_name": "New Bijang", "ward_id": "0"}, {"ward_no": "0", "ward_name": "New Khuakual", "ward_id": "0"}, {"ward_no": "0", "ward_name": "Pantha", "ward_id": "0"}, {"ward_no": "0", "ward_name": "Phaisan", "ward_id": "0"}, {"ward_no": "0", "ward_name": "P.Khomunnom", "ward_id": "0"}, {"ward_no": "0", "ward_name": "P.N.Khovong", "ward_id": "0"}, {"ward_no": "0", "ward_name": "Saiboh", "ward_id": "0"}, {"ward_no": "0", "ward_name": "Sangaikot", "ward_id": "0"}, {"ward_no": "0", "ward_name": "Selshi", "ward_id": "0"}, {"ward_no": "0", "ward_name": "S.Gelbung", "ward_id": "0"}, {"ward_no": "0", "ward_name": "Singheu", "ward_id": "0"}, {"ward_no": "0", "ward_name": "SL.Molcham", "ward_id": "0"}, {"ward_no": "0", "ward_name": "S.Mongkot", "ward_id": "0"}, {"ward_no": "0", "ward_name": "Songpeh", "ward_id": "0"}, {"ward_no": "0", "ward_name": "Suanggual", "ward_id": "0"}, {"ward_no": "0", "ward_name": "T.Bongpijang", "ward_id": "0"}, {"ward_no": "0", "ward_name": "Teisaljang", "ward_id": "0"}, {"ward_no": "0", "ward_name": "T. Gamnomjang", "ward_id": "0"}, {"ward_no": "0", "ward_name": "T.Khonom", "ward_id": "0"}, {"ward_no": "0", "ward_name": "T.Khuangkhai", "ward_id": "0"}, {"ward_no": "0", "ward_name": "T.Lailoiphai", "ward_id": "0"}, {"ward_no": "0", "ward_name": "T.Leijang", "ward_id": "0"}, {"ward_no": "0", "ward_name": "T. Munnuam", "ward_id": "0"}, {"ward_no": "0", "ward_name": "T.Phaijol", "ward_id": "0"}, {"ward_no": "0", "ward_name": "Tuidam", "ward_id": "0"}, {"ward_no": "0", "ward_name": "Tuining", "ward_id": "0"}, {"ward_no": "0", "ward_name": "Tuiningkhal", "ward_id": "0"}, {"ward_no": "0", "ward_name": "Tuinuphai", "ward_id": "0"}, {"ward_no": "0", "ward_name": "Tuisomjang", "ward_id": "0"}, {"ward_no": "0", "ward_name": "Tuitengjang", "ward_id": "0"}, {"ward_no": "0", "ward_name": "Tuitum (J)", "ward_id": "0"}, {"ward_no": "0", "ward_name": "Tuiveiphai", "ward_id": "0"}, {"ward_no": "0", "ward_name": "Tuivelmual", "ward_id": "0"}, {"ward_no": "0", "ward_name": "Walkhu", "ward_id": "0"}, {"ward_no": "0", "ward_name": "W. Joujang", "ward_id": "0"}, {"ward_no": "0", "ward_name": "Zalenkot", "ward_id": "0"}, {"ward_no": "0", "ward_name": "Z.Khomunnom", "ward_id": "0"}, {"ward_no": "0", "ward_name": "Zobethel", "ward_id": "0"}, {"ward_no": "0", "ward_name": "Zomi Zion", "ward_id": "0"}]}