{"name": "Keirao Bitra", "lsg_code": "6", "district": "Imphal East", "state": "Manipur", "no_of_wards": 46, "wards": [{"ward_no": 202, "ward_name": "Andro", "ward_id": 202}, {"ward_no": 203, "ward_name": "Andro Khunou And Kamu Yaithibi", "ward_id": 203}, {"ward_no": 204, "ward_name": "Angtha", "ward_id": 204}, {"ward_no": 205, "ward_name": "Arapti", "ward_id": 205}, {"ward_no": 206, "ward_name": "Arapti(Excluding N.A)", "ward_id": 206}, {"ward_no": 207, "ward_name": "Bamon Kampu", "ward_id": 207}, {"ward_no": 208, "ward_name": "Chanam Sandrok", "ward_id": 208}, {"ward_no": 209, "ward_name": "Changamdabi Mathak Makha And Mamang", "ward_id": 209}, {"ward_no": 210, "ward_name": "Gangapat", "ward_id": 210}, {"ward_no": 211, "ward_name": "Huikap And Ngariyan Muslim", "ward_id": 211}, {"ward_no": 212, "ward_name": "Itham", "ward_id": 212}, {"ward_no": 213, "ward_name": "Kaina", "ward_id": 213}, {"ward_no": 214, "ward_name": "Kalika", "ward_id": 214}, {"ward_no": 215, "ward_name": "Karpur Shungba Kabui", "ward_id": 215}, {"ward_no": 216, "ward_name": "Keirao Makting", "ward_id": 216}, {"ward_no": 217, "ward_name": "Keirao-Bitra And Chingdong Kabui", "ward_id": 217}, {"ward_no": 218, "ward_name": "Keirao-Langdum", "ward_id": 218}, {"ward_no": 219, "ward_name": "Keirao-Wangkhem", "ward_id": 219}, {"ward_no": 220, "ward_name": "Khanarok(Khandrok)", "ward_id": 220}, {"ward_no": 221, "ward_name": "Kiyamgei Awang Leikai And Kiyamgei Mayai Leikai", "ward_id": 221}, {"ward_no": 222, "ward_name": "Kiyamgei Muslim", "ward_id": 222}, {"ward_no": 223, "ward_name": "Kongba Nandeibam Leikai", "ward_id": 223}, {"ward_no": 224, "ward_name": "Kongbam Nongthongbam Leikai Southern Laishram", "ward_id": 224}, {"ward_no": 225, "ward_name": "Langthrei Loukon", "ward_id": 225}, {"ward_no": 226, "ward_name": "Lemba Khul", "ward_id": 226}, {"ward_no": 227, "ward_name": "Lilong Kabui Shantipur", "ward_id": 227}, {"ward_no": 228, "ward_name": "Loumanbi", "ward_id": 228}, {"ward_no": 229, "ward_name": "Machahal", "ward_id": 229}, {"ward_no": 230, "ward_name": "Monthou Keithelmanbi And Laikhong", "ward_id": 230}, {"ward_no": 231, "ward_name": "Nungaipokpi", "ward_id": 231}, {"ward_no": 232, "ward_name": "Nungbrang", "ward_id": 232}, {"ward_no": 233, "ward_name": "Phunan Maring", "ward_id": 233}, {"ward_no": 234, "ward_name": "Poiroukhongjil", "ward_id": 234}, {"ward_no": 235, "ward_name": "Takhok Makha", "ward_id": 235}, {"ward_no": 236, "ward_name": "Thiyam-Konjil", "ward_id": 236}, {"ward_no": 237, "ward_name": "Top-Chingtha Laimanai", "ward_id": 237}, {"ward_no": 238, "ward_name": "Tulihal (Amujao Salam Awang Fr Kaina Rd To Tbl Rvr", "ward_id": 238}, {"ward_no": 239, "ward_name": "Tulihal (Amujao Salam Makha Fr Kaina Rd To Tbl Rvr", "ward_id": 239}, {"ward_no": 240, "ward_name": "Tumukhong Moirang Purel", "ward_id": 240}, {"ward_no": 241, "ward_name": "Uchekon", "ward_id": 241}, {"ward_no": 242, "ward_name": "Uchekon Khunou", "ward_id": 242}, {"ward_no": 243, "ward_name": "Uchekon Kshetri Leikai", "ward_id": 243}, {"ward_no": 244, "ward_name": "Uchekon Nandeibam Leikai", "ward_id": 244}, {"ward_no": 245, "ward_name": "Urup", "ward_id": 245}, {"ward_no": 246, "ward_name": "Yambem And Yambem Khunou", "ward_id": 246}, {"ward_no": 247, "ward_name": "Takhok Mapal (Awang)", "ward_id": 247}]}
